LICENSE
MANIFEST.in
README.rst
setup.py
twunnel3/__init__.py
twunnel3/local_proxy_server.py
twunnel3/local_proxy_server__https.py
twunnel3/local_proxy_server__socks4.py
twunnel3/local_proxy_server__socks5.py
twunnel3/local_proxy_server__ssl.py
twunnel3/logger.py
twunnel3/proxy_server.py
twunnel3/proxy_server__https.py
twunnel3/proxy_server__socks4.py
twunnel3/proxy_server__socks5.py
twunnel3/remote_proxy_server.py
twunnel3/remote_proxy_server__ssl.py
twunnel3.egg-info/PKG-INFO
twunnel3.egg-info/SOURCES.txt
twunnel3.egg-info/dependency_links.txt
twunnel3.egg-info/requires.txt
twunnel3.egg-info/top_level.txt