Metadata-Version: 1.1
Name: twunnel3
Version: 0.3.0
Summary: A HTTPS/SOCKS4/SOCKS5 tunnel for AsyncIO.
Home-page: https://github.com/jvansteirteghem/twunnel3
Author: Jeroen Van Steirteghem
Author-email: jeroen.vansteirteghem@gmail.com
License: MIT
Platform: UNKNOWN
Classifier: Programming Language :: Python
Classifier: Programming Language :: Python :: 3
Classifier: Programming Language :: Python :: 3.3
